LICENSE.txt
README.md
setup.cfg
setup.py
carreiras_commons/__init__.py
carreiras_commons/config.py
carreiras_commons.egg-info/PKG-INFO
carreiras_commons.egg-info/SOURCES.txt
carreiras_commons.egg-info/dependency_links.txt
carreiras_commons.egg-info/top_level.txt
carreiras_commons/enum/email_enum.py
carreiras_commons/enum/notificacao_adm_enum.py
carreiras_commons/enum/notificacao_enum.py
carreiras_commons/messaging/messaging_email.py
carreiras_commons/messaging/messaging_notificacao.py
carreiras_commons/messaging/messaging_notificacao_admin.py
carreiras_commons/seguranca/__init__.py
carreiras_commons/seguranca/util/decorators.py
carreiras_commons/seguranca/util/jwt_token.py
carreiras_commons/util/exceptions.py
carreiras_commons/util/license.py
carreiras_commons/util/local_file.py
carreiras_commons/util/logger_app.py