Metadata-Version: 2.1
Name: carreiras-commons
Version: 0.0.16
Summary: Common functions to carreiras projects
Home-page: https://dev.azure.com/TITBrasil/Carreiras/_git/CARREIRAS-COMMON
Author: HYTI
Author-email: contato@titcs.com.br
License: MIT
Project-URL: Código fonte, https://TITBrasil@dev.azure.com/TITBrasil/Carreiras/_git/CARREIRAS-COMMON
Project-URL: Download, https://TITBrasil@dev.azure.com/TITBrasil/Carreiras/_git/CARREIRAS-COMMON
Keywords: carreiras
Platform: UNKNOWN
Classifier: Development Status :: 5 - Production/Stable
Classifier: Intended Audience :: Developers
Classifier: License :: OSI Approved :: MIT License
Classifier: Natural Language :: Portuguese (Brazilian)
Classifier: Operating System :: OS Independent
Classifier: Topic :: Software Development :: Internationalization
Classifier: Topic :: Scientific/Engineering :: Physics
License-File: LICENSE.txt
